design.sv
/// Code your design here
module tailLight(clk,rst,lt,rt,haz,li,ri);
  
  input clk,rst,lt,rt,haz;
  reg [2:0] ps,ns;
  parameter s0=3'd0,s1=3'd1,s2=3'd2,s3=3'd3,s4=3'd4,s5=3'd5;
  output reg [2:0] li=0;
  output reg [2:0] ri=0;
  
  always@(posedge clk)
    begin
      if(rst)
        ps <= s0;
      else
        ps <= ns;
    end
  
  always@(posedge clk or negedge clk)
    begin
      if(haz)
        begin
          if(rst)
            ps <= s0;
          else
            ps <= ns;
        end
    end
  
  always@(lt,rt,haz,ps)
    begin
      if(haz)
        begin
          case(ps)
            s0: begin {li,ri}=6'b000000; ns = s1; end
            s1: begin {li,ri}=6'b100001; ns = s2; end
            s2: begin {li,ri}=6'b110011; ns = s3; end
            s3: begin {li,ri}=6'b111111; ns = s4; end
            s4: begin {li,ri}=6'b110011; ns = s5; end
            s5: begin {li,ri}=6'b100001; ns = s0; end
            default: begin {li,ri}=6'b000000; end
          endcase
        end
      else
        begin
          if(lt || rt)
            begin
              case(ps)
                s0: begin if(lt) {li,ri}=6'b000000; if(rt) {li,ri}=6'b000000; ns=s1; end
                s1: begin if(lt) {li,ri}=6'b100000; if(rt) {li,ri}=6'b000001; ns=s2; end
                s2: begin if(lt) {li,ri}=6'b110000; if(rt) {li,ri}=6'b000011; ns=s3; end
                s3: begin if(lt) {li,ri}=6'b111000; if(rt) {li,ri}=6'b000111; ns=s4; end
                default: {li,ri}=6'b000000;
              endcase
            end
        end
    end
endmodule

testbench.sv
// Code your testbench here
// or browse Examples
module tailLight_tb;
  
  reg HAZARD,r,l,clk,rst;
  wire [2:0] RIGHT_INDICATOR, LEFT_INDICATOR;
  tailLight DUT (clk,rst,l,r,HAZARD,LEFT_INDICATOR,RIGHT_INDICATOR);
  
  initial clk=0;
  always #10 clk=~clk;
  
  initial
    begin
      #10 HAZARD=0;rst=1;r=0;l=1;
      #90 l=0;
      #100 HAZARD=0;rst=0;r=0;l=1;
      #100 HAZARD=1;l=0;
      #130 HAZARD=0;r=1;
    end
  
  initial
    begin
      $dumpfile("taillight.vcd");
      $dumpvars;
      #700 $finish;
    end
endmodule

taillight.vcd
$date
	Thu Apr  4 00:45:57 2024
$end
$version
	QuestaSim Version 2021.3
$end
$timescale
	1ns
$end

$scope module tailLight_tb $end
$var wire 3 ! LEFT_INDICATOR [2:0] $end
$var wire 3 " RIGHT_INDICATOR [2:0] $end
$var reg 1 # HAZARD $end
$var reg 1 $ clk $end
$var reg 1 % l $end
$var reg 1 & r $end
$var reg 1 ' rst $end

$scope module DUT $end
$var wire 1 ( clk $end
$var wire 1 ) haz $end
$var wire 1 * lt $end
$var wire 1 + rst $end
$var wire 1 , rt $end
$var parameter 3 - s0 $end
$var parameter 3 . s1 $end
$var parameter 3 / s2 $end
$var parameter 3 0 s3 $end
$var parameter 3 1 s4 $end
$var parameter 3 2 s5 $end
$var reg 3 3 li [2:0] $end
$var reg 3 4 ns [2:0] $end
$var reg 3 5 ps [2:0] $end
$var reg 3 6 ri [2:0] $end
$upscope $end
$upscope $end

$scope begin std $end
$upscope $end
$enddefinitions $end
#0
$dumpvars
b0 !
b0 "
0(
x+
x*
x,
x)
x#
0$
x%
x&
x'
b0 -
b1 .
b10 /
b11 0
b100 1
b101 2
b0 3
bx 4
bx 5
b0 6
$end
#10
1$
0#
1'
0&
1%
1+
1*
0,
0)
1(
b0 5
b1 4
#20
0$
0(
#30
1$
1(
#40
0$
0(
#50
1$
1(
#60
0$
0(
#70
1$
1(
#80
0$
0(
#90
1$
1(
#100
0%
0$
0(
0*
#110
1$
1(
#120
0$
0(
#130
1$
1(
#140
0$
0(
#150
1$
1(
#160
0$
0(
#170
1$
1(
#180
0$
0(
#190
1$
1(
#200
0'
1%
0$
0+
0(
1*
#210
1$
1(
b1 5
b100 3
b10 4
b100 !
#220
0$
0(
#230
1$
1(
b10 5
b110 3
b11 4
b110 !
#240
0$
0(
#250
1$
1(
b11 5
b111 3
b100 4
b111 !
#260
0$
0(
#270
1$
1(
b100 5
b0 3
b0 !
#280
0$
0(
#290
1$
1(
#300
1#
0%
0$
0(
0*
1)
b11 6
b110 3
b101 4
b110 !
b11 "
#310
1$
1(
b101 5
b1 6
b100 3
b0 4
b100 !
b1 "
#320
0$
0(
b0 5
b0 6
b0 3
b1 4
b0 !
b0 "
#330
1$
1(
b1 5
b1 6
b100 3
b10 4
b100 !
b1 "
#340
0$
0(
b10 5
b11 6
b110 3
b11 4
b110 !
b11 "
#350
1$
1(
b11 5
b111 6
b111 3
b100 4
b111 !
b111 "
#360
0$
0(
b100 5
b11 6
b110 3
b101 4
b110 !
b11 "
#370
1$
1(
b101 5
b1 6
b100 3
b0 4
b100 !
b1 "
#380
0$
0(
b0 5
b0 6
b0 3
b1 4
b0 !
b0 "
#390
1$
1(
b1 5
b1 6
b100 3
b10 4
b100 !
b1 "
#400
0$
0(
b10 5
b11 6
b110 3
b11 4
b110 !
b11 "
#410
1$
1(
b11 5
b111 6
b111 3
b100 4
b111 !
b111 "
#420
0$
0(
b100 5
b11 6
b110 3
b101 4
b110 !
b11 "
#430
0#
1&
1$
1(
1,
0)
b0 6
b0 3
b0 !
b0 "
b101 5
